to_shell/__init__.py
to_shell/to_shell.py
to_shell-2.0.0.dist-info/LICENSE
to_shell-2.0.0.dist-info/METADATA
to_shell-2.0.0.dist-info/WHEEL
to_shell-2.0.0.dist-info/top_level.txt
to_shell-2.0.0.dist-info/RECORD
